topsis_create/__init__.py
topsis_create/topsis_cal.py
TOPSIS_Paras_101983048-1.0.3.dist-info/METADATA
TOPSIS_Paras_101983048-1.0.3.dist-info/WHEEL
TOPSIS_Paras_101983048-1.0.3.dist-info/licence.txt
TOPSIS_Paras_101983048-1.0.3.dist-info/top_level.txt
TOPSIS_Paras_101983048-1.0.3.dist-info/RECORD
